pykechain/__about__.py
pykechain/__init__.py
pykechain/client.py
pykechain/client_utils.py
pykechain/defaults.py
pykechain/enums.py
pykechain/exceptions.py
pykechain/extra_utils.py
pykechain/helpers.py
pykechain/py.typed
pykechain/typing.py
pykechain/utils.py
pykechain/models/__init__.py
pykechain/models/activity.py
pykechain/models/activity2.py
pykechain/models/association.py
pykechain/models/banner.py
pykechain/models/base.py
pykechain/models/base_reference.py
pykechain/models/context.py
pykechain/models/expiring_download.py
pykechain/models/form.py
pykechain/models/input_checks.py
pykechain/models/notification.py
pykechain/models/part.py
pykechain/models/part2.py
pykechain/models/partset.py
pykechain/models/property.py
pykechain/models/property2.py
pykechain/models/property2_activity_reference.py
pykechain/models/property2_attachment.py
pykechain/models/property2_datetime.py
pykechain/models/property2_multi_reference.py
pykechain/models/property2_selectlist.py
pykechain/models/property_attachment.py
pykechain/models/property_datetime.py
pykechain/models/property_multi_reference.py
pykechain/models/property_reference.py
pykechain/models/property_selectlist.py
pykechain/models/scope.py
pykechain/models/scope2.py
pykechain/models/service.py
pykechain/models/stored_file.py
pykechain/models/tags.py
pykechain/models/team.py
pykechain/models/tree_traversal.py
pykechain/models/user.py
pykechain/models/value_filter.py
pykechain/models/workflow.py
pykechain/models/representations/__init__.py
pykechain/models/representations/component.py
pykechain/models/representations/representation_base.py
pykechain/models/representations/representations.py
pykechain/models/sidebar/__init__.py
pykechain/models/sidebar/sidebar_base.py
pykechain/models/sidebar/sidebar_button.py
pykechain/models/sidebar/sidebar_card.py
pykechain/models/sidebar/sidebar_manager.py
pykechain/models/validators/__init__.py
pykechain/models/validators/effects.py
pykechain/models/validators/mime_types_defaults.py
pykechain-4.16.1.dist-info/licenses/LICENSE
pykechain-4.16.1.dist-info/METADATA
pykechain-4.16.1.dist-info/WHEEL
pykechain-4.16.1.dist-info/top_level.txt
pykechain-4.16.1.dist-info/RECORD
