Metadata-Version: 2.4
Name: pykechain
Version: 4.16.1
Summary: KE-chain Python SDK
Home-page: https://github.com/KE-works/pykechain
Author: KE-works BV
Author-email: support+pykechain@ke-works.com
License: Apache Open Source License 2.0
Project-URL: Documentation, https://pykechain.readthedocs.io/en/latest
Project-URL: Changelog, https://github.com/KE-works/pykechain/blob/master/CHANGELOG.rst
Project-URL: Source, https://github.com/KE-works/pykechain/
Project-URL: Tracker, https://github.com/KE-works/pykechain/issues
Project-URL: Company Page, https://ke-chain.com
Keywords: python api rest sdk KE-chain
Classifier: Development Status :: 5 - Production/Stable
Classifier: Intended Audience :: Developers
Classifier: Topic :: Software Development :: Libraries
Classifier: Topic :: Scientific/Engineering
Classifier: License :: OSI Approved :: Apache Software License
Classifier: Programming Language :: Python :: 3 :: Only
Classifier: Programming Language :: Python :: 3
Classifier: Programming Language :: Python :: 3.7
Classifier: Programming Language :: Python :: 3.8
Classifier: Programming Language :: Python :: 3.9
Classifier: Programming Language :: Python :: 3.10
Classifier: Programming Language :: Python :: 3.11
Classifier: Programming Language :: Python :: 3.12
Classifier: Programming Language :: Python :: Implementation :: PyPy
Classifier: Operating System :: MacOS
Classifier: Operating System :: Microsoft :: Windows
Classifier: Operating System :: POSIX :: Linux
Requires-Python: >=3.7
License-File: LICENSE
Requires-Dist: requests>=2.20.0
Requires-Dist: envparse
Requires-Dist: typing
Requires-Dist: six
Requires-Dist: jsonschema
Requires-Dist: semver>=2.10.0
Requires-Dist: pytz
Dynamic: author
Dynamic: author-email
Dynamic: classifier
Dynamic: description
Dynamic: description-content-type
Dynamic: home-page
Dynamic: keywords
Dynamic: license
Dynamic: license-file
Dynamic: project-url
Dynamic: requires-dist
Dynamic: requires-python
Dynamic: summary
